jmorder/__init__.py
jmorder-0.3.dist-info/METADATA
jmorder-0.3.dist-info/WHEEL
jmorder-0.3.dist-info/top_level.txt
jmorder-0.3.dist-info/RECORD
